__init__.py
robocop_mcp/__init__.py
robocop_mcp/__main__.py
robocop_mcp/config.py
robocop_mcp/mcp_check.py
robocop_mcp/mcp_format.py
robocop_mcp/server.py
robocop_mcp/rules/ARG01_unused-argument.md
robocop_mcp/rules/ARG04_undefined-argument-value.md
robocop_mcp/rules/ARG06_unused-argument.md
robocop_mcp/rules/ARG07_arguments-per-line.md
robocop_mcp/rules/COM02_missing-space-after-comment.md
robocop_mcp/rules/DEPR02_deprecated-statement.md
robocop_mcp/rules/DEPR05_replace-set-variable-with-var.md
robocop_mcp/rules/DEPR06_replace-create-with-var.md
robocop_mcp/rules/DUP01_duplicated-test-case.md
robocop_mcp/rules/DUP02_duplicated-keyword.md
robocop_mcp/rules/DUP03_duplicated-variable.md
robocop_mcp/rules/DUP04_duplicated-resource.md
robocop_mcp/rules/ERR01_parsing-error.md
robocop_mcp/rules/ERR13_invalid-if.md
robocop_mcp/rules/IMP02_builtin-imports-not-sorted.md
robocop_mcp/rules/KW01_sleep-keyword-used.md
robocop_mcp/rules/LEN01_too-long-keyword.md
robocop_mcp/rules/LEN03_too-many-calls-in-keyword.md
robocop_mcp/rules/LEN04_too-long-test-case.md
robocop_mcp/rules/LEN05_too-few-calls-in-test-case.md
robocop_mcp/rules/LEN06_too-many-calls-in-test-case.md
robocop_mcp/rules/LEN08_line-too-long.md
robocop_mcp/rules/LEN09_empty-section.md
robocop_mcp/rules/LEN28_file-too-long.md
robocop_mcp/rules/MISC06_can-be-resource-file.md
robocop_mcp/rules/MISC07_if-can-be-merged.md
robocop_mcp/rules/MISC08_statement-outside-loop.md
robocop_mcp/rules/MISC09_inline-if-can-be-used.md
robocop_mcp/rules/MISC11_multiline-inline-if.md
robocop_mcp/rules/MISC13_expression-can-be-simplified.md
robocop_mcp/rules/MISC15_unused-disabler.md
robocop_mcp/rules/NAME01_not-allowed-char-in-name.md
robocop_mcp/rules/NAME02_wrong-case-in-keyword-name.md
robocop_mcp/rules/NAME03_keyword-name-is-reserved-word.md
robocop_mcp/rules/NAME07_not-capitalized-test-case-title.md
robocop_mcp/rules/NAME08_section-variable-not-uppercase.md
robocop_mcp/rules/README.md
robocop_mcp/rules/SPC06_mixed-tabs-and-spaces.md
robocop_mcp-1.8.0.dist-info/licenses/LICENSE
robocop_mcp-1.8.0.dist-info/METADATA
robocop_mcp-1.8.0.dist-info/WHEEL
robocop_mcp-1.8.0.dist-info/entry_points.txt
robocop_mcp-1.8.0.dist-info/top_level.txt
robocop_mcp-1.8.0.dist-info/RECORD
