Metadata-Version: 2.4
Name: robocop-mcp
Version: 1.8.0
Summary: MCP server for helping user to resolve Robot Framework code issues detected by Robocop.
Author-email: Tatu Aalto <aalto.tatu@gmail.com>
License-Expression: MIT
Project-URL: Homepage, https://github.com/aaltat/robocop-mcp
Project-URL: Repository, https://github.com/aaltat/robocop-mcp
Project-URL: Issues, https://github.com/aaltat/robocop-mcp/issues
Project-URL: Documentation, https://github.com/aaltat/robocop-mcp/blob/main/README.md
Keywords: robotframework,robocop,mcp,server,code quality,linting
Classifier: Development Status :: 5 - Production/Stable
Classifier: Operating System :: OS Independent
Classifier: Programming Language :: Python :: 3
Classifier: Topic :: Software Development :: Testing
Classifier: Topic :: Software Development :: Quality Assurance
Classifier: Topic :: Utilities
Classifier: Framework :: Robot Framework
Classifier: Framework :: Robot Framework :: Tool
Classifier: Intended Audience :: Developers
Requires-Python: >=3.10.11
License-File: LICENSE
Requires-Dist: httpx>=0.28.1
Requires-Dist: mcp[cli]>=1.22.0
Requires-Dist: robotframework-robocop>=7.0.0
Requires-Dist: tomli>=2.2.1
Dynamic: license-file
